irds/__init__.py
irds/rds.py
irds-0.0.2.dist-info/LICENSE
irds-0.0.2.dist-info/METADATA
irds-0.0.2.dist-info/WHEEL
irds-0.0.2.dist-info/top_level.txt
irds-0.0.2.dist-info/RECORD
